openfatture/__init__.py
openfatture/ai/__init__.py
openfatture/ai/agents/__init__.py
openfatture/ai/agents/cash_flow_predictor.py
openfatture/ai/agents/chat_agent.py
openfatture/ai/agents/invoice_assistant.py
openfatture/ai/agents/models.py
openfatture/ai/agents/payment_insight_agent.py
openfatture/ai/agents/tax_advisor.py
openfatture/ai/agents/compliance/__init__.py
openfatture/ai/agents/compliance/checker.py
openfatture/ai/agents/compliance/heuristics.py
openfatture/ai/agents/compliance/rules.py
openfatture/ai/agents/compliance/sdi_patterns.py
openfatture/ai/cache/__init__.py
openfatture/ai/cache/config.py
openfatture/ai/cache/memory.py
openfatture/ai/cache/provider.py
openfatture/ai/cache/strategy.py
openfatture/ai/config/__init__.py
openfatture/ai/config/settings.py
openfatture/ai/context/__init__.py
openfatture/ai/context/enrichment.py
openfatture/ai/domain/__init__.py
openfatture/ai/domain/agent.py
openfatture/ai/domain/context.py
openfatture/ai/domain/message.py
openfatture/ai/domain/prompt.py
openfatture/ai/domain/response.py
openfatture/ai/ml/__init__.py
openfatture/ai/ml/config.py
openfatture/ai/ml/data_loader.py
openfatture/ai/ml/features.py
openfatture/ai/orchestration/__init__.py
openfatture/ai/orchestration/human_loop.py
openfatture/ai/orchestration/resilience.py
openfatture/ai/orchestration/states.py
openfatture/ai/orchestration/workflows/__init__.py
openfatture/ai/orchestration/workflows/cash_flow_analysis.py
openfatture/ai/orchestration/workflows/compliance_check.py
openfatture/ai/orchestration/workflows/invoice_creation.py
openfatture/ai/prompts/__init__.py
openfatture/ai/prompts/chat_assistant.yaml
openfatture/ai/prompts/invoice_assistant.yaml
openfatture/ai/prompts/tax_advisor.yaml
openfatture/ai/providers/__init__.py
openfatture/ai/providers/anthropic.py
openfatture/ai/providers/base.py
openfatture/ai/providers/factory.py
openfatture/ai/providers/ollama.py
openfatture/ai/providers/openai.py
openfatture/ai/rag/__init__.py
openfatture-1.1.0.dist-info/METADATA
openfatture-1.1.0.dist-info/WHEEL
openfatture-1.1.0.dist-info/entry_points.txt
openfatture-1.1.0.dist-info/licenses/LICENSE
openfatture-1.1.0.dist-info/RECORD
