Metadata-Version: 2.4
Name: openfatture
Version: 1.1.0
Summary: Open-source electronic invoicing for Italian freelancers - CLI-first with AI workflows
Project-URL: Homepage, https://github.com/gianlucamazza/openfatture
Project-URL: Repository, https://github.com/gianlucamazza/openfatture
Project-URL: Issues, https://github.com/gianlucamazza/openfatture/issues
Author-email: Gianluca Mazza <info@gianlucamazza.it>
License: MIT
License-File: LICENSE
Keywords: ai,cli,fattura-elettronica,fatturapa,freelance,invoicing,sdi
Classifier: Development Status :: 3 - Alpha
Classifier: Intended Audience :: Developers
Classifier: Intended Audience :: End Users/Desktop
Classifier: License :: OSI Approved :: MIT License
Classifier: Programming Language :: Python :: 3.12
Classifier: Programming Language :: Python :: 3.13
Classifier: Topic :: Office/Business :: Financial :: Accounting
Requires-Python: >=3.12
Requires-Dist: alembic>=1.13.1
Requires-Dist: anthropic>=0.18.0
Requires-Dist: asn1crypto>=1.5.1
Requires-Dist: chromadb>=0.4.22
Requires-Dist: click>=8.1.7
Requires-Dist: cryptography>=42.0.2
Requires-Dist: httpx>=0.26.0
Requires-Dist: jinja2>=3.1.0
Requires-Dist: langchain-community>=0.0.17
Requires-Dist: langchain-core>=0.1.20
Requires-Dist: langchain>=0.1.6
Requires-Dist: langgraph>=0.0.20
Requires-Dist: lxml>=5.1.0
Requires-Dist: ofxparse>=0.21
Requires-Dist: openai>=1.12.0
Requires-Dist: pandas>=2.3.3
Requires-Dist: prophet>=1.1.5
Requires-Dist: pyasn1-modules>=0.3.0
Requires-Dist: pyasn1>=0.5.0
Requires-Dist: pydantic-settings>=2.1.0
Requires-Dist: pydantic>=2.6.0
Requires-Dist: python-dateutil>=2.8.2
Requires-Dist: python-dotenv>=1.0.0
Requires-Dist: questionary>=2.0.0
Requires-Dist: rapidfuzz>=3.0.0
Requires-Dist: reportlab>=4.0.9
Requires-Dist: requests>=2.31.0
Requires-Dist: rich>=13.7.0
Requires-Dist: sentence-transformers>=2.6.0
Requires-Dist: sqlalchemy>=2.0.25
Requires-Dist: structlog>=24.1.0
Requires-Dist: tiktoken>=0.8.0
Requires-Dist: typer[all]>=0.12.0
Requires-Dist: xgboost>=2.1.0
Requires-Dist: xmlschema>=3.0.1
Provides-Extra: dev
Requires-Dist: black>=25.9.0; extra == 'dev'
Requires-Dist: bump-my-version>=0.18.0; extra == 'dev'
Requires-Dist: hypothesis>=6.98.0; extra == 'dev'
Requires-Dist: isort>=5.13.2; extra == 'dev'
Requires-Dist: mypy>=1.8.0; extra == 'dev'
Requires-Dist: pandas-stubs>=2.0.0; extra == 'dev'
Requires-Dist: pre-commit>=3.6.0; extra == 'dev'
Requires-Dist: pytest-asyncio>=0.23.3; extra == 'dev'
Requires-Dist: pytest-benchmark>=4.0.0; extra == 'dev'
Requires-Dist: pytest-cov>=4.1.0; extra == 'dev'
Requires-Dist: pytest-mock>=3.12.0; extra == 'dev'
Requires-Dist: pytest>=8.0.0; extra == 'dev'
Requires-Dist: ruff>=0.14.0; extra == 'dev'
Requires-Dist: types-pyasn1>=0.5.0; extra == 'dev'
Requires-Dist: types-pyyaml>=6.0.0; extra == 'dev'
Requires-Dist: types-reportlab>=4.0.0; extra == 'dev'
Requires-Dist: types-requests>=2.31.0; extra == 'dev'
